{"cisco": {"aci": {"quality_score": null, "score": 4.9, "count": 14, "docs": 4.5, "ease_of_use": 5, "does_what_it_says": 5, "works_as_is": 5, "used_in_production": 5}, "ios": {"quality_score": null, "score": 4.2, "count": 6, "docs": 4.3, "ease_of_use": 4.5, "does_what_it_says": 4.3, "works_as_is": 4.3, "used_in_production": 4.3}, "nxos": {"quality_score": null, "score": 5.0, "count": 2, "docs": 5, "ease_of_use": 5, "does_what_it_says": 5, "works_as_is": 5, "used_in_production": 5}, "dcnm": {"quality_score": null, "score": 5.0, "count": 1, "docs": 5, "ease_of_use": 5, "does_what_it_says": 5, "works_as_is": 5, "used_in_production": 5}, "meraki": {"quality_score": null, "score": 4.8, "count": 1, "docs": 4, "ease_of_use": 5, "does_what_it_says": 5, "works_as_is": 5, "used_in_production": 5}, "ise": {"quality_score": null, "score": 5.0, "count": 1, "docs": 5, "ease_of_use": 5, "does_what_it_says": 5, "works_as_is": 5, "used_in_production": 5}, "fmcansible": {"quality_score": null, "score": 4.8, "count": 1, "docs": 4, "ease_of_use": 5, "does_what_it_says": 5, "works_as_is": 5, "used_in_production": 5}}, "community": {"general": {"quality_score": null, "score": 4.0, "count": 10, "docs": 3.6, "ease_of_use": 4, "does_what_it_says": 4.5, "works_as_is": 4.5, "used_in_production": 4.5}, "zabbix": {"quality_score": null, "score": 4.8, "count": 6, "docs": 4.8, "ease_of_use": 4.8, "does_what_it_says": 5, "works_as_is": 4.3, "used_in_production": 5}, "crypto": {"quality_score": null, "score": 5.0, "count": 3, "docs": 5, "ease_of_use": 5, "does_what_it_says": 5, "works_as_is": 5, "used_in_production": 5}, "postgresql": {"quality_score": null, "score": 4.3, "count": 3, "docs": 5, "ease_of_use": 5, "does_what_it_says": 5, "works_as_is": 3.7, "used_in_production": 3.7}, "mysql": {"quality_score": null, "score": 4.8, "count": 3, "docs": 4.7, "ease_of_use": 4.3, "does_what_it_says": 5, "works_as_is": 5, "used_in_production": 5}, "docker": {"quality_score": null, "score": 4.1, "count": 3, "docs": 3.3, "ease_of_use": 5, "does_what_it_says": 5, "works_as_is": 5, "used_in_production": 5}, "cassandra": {"quality_score": null, "score": 4.5, "count": 2, "docs": 3, "ease_of_use": 5, "does_what_it_says": 5, "works_as_is": 5, "used_in_production": 5}, "vmware": {"quality_score": null, "score": 4.6, "count": 2, "docs": 4.5, "ease_of_use": 4, "does_what_it_says": 5, "works_as_is": 5, "used_in_production": 5}, "grafana": {"quality_score": null, "score": 4.6, "count": 2, "docs": 4, "ease_of_use": 4.5, "does_what_it_says": 5, "works_as_is": 5, "used_in_production": 5}, "ciscosmb": {"quality_score": null, "score": 3.2, "count": 2, "docs": 4, "ease_of_use": 5, "does_what_it_says": 3, "works_as_is": 3, "used_in_production": 3}, "windows": {"quality_score": null, "score": 4.0, "count": 2, "docs": 2.5, "ease_of_use": 5, "does_what_it_says": 5, "works_as_is": 5, "used_in_production": 5}, "molecule": {"quality_score": null, "score": 5.0, "count": 2, "docs": 5, "ease_of_use": 5, "does_what_it_says": 5, "works_as_is": 5, "used_in_production": 5}, "proxysql": {"quality_score": null, "score": 5.0, "count": 2, "docs": 5, "ease_of_use": 5, "does_what_it_says": 5, "works_as_is": 5, "used_in_production": 5}, "mongodb": {"quality_score": null, "score": null, "count": 1, "docs": 1, "ease_of_use": 1, "does_what_it_says": null, "works_as_is": null, "used_in_production": null}, "aws": {"quality_score": null, "score": null, "count": 1, "docs": 1, "ease_of_use": null, "does_what_it_says": null, "works_as_is": null, "used_in_production": null}, "network": {"quality_score": null, "score": 5.0, "count": 1, "docs": 5, "ease_of_use": 5, "does_what_it_says": 5, "works_as_is": 5, "used_in_production": null}, "digitalocean": {"quality_score": null, "score": 3.8, "count": 1, "docs": 1, "ease_of_use": 4, "does_what_it_says": 5, "works_as_is": 5, "used_in_production": 5}, "google": {"quality_score": null, "score": null, "count": 1, "docs": 1, "ease_of_use": null, "does_what_it_says": null, "works_as_is": null, "used_in_production": null}, "vagrant": {"quality_score": null, "score": 5.0, "count": 1, "docs": 5, "ease_of_use": 5, "does_what_it_says": 5, "works_as_is": 5, "used_in_production": 5}}, "fortinet": {"fortios": {"quality_score": null, "score": 4.0, "count": 9, "docs": 4.2, "ease_of_use": 3.9, "does_what_it_says": 4.6, "works_as_is": 3.7, "used_in_production": 4.6}, "fortimanager": {"quality_score": null, "score": 4.6, "count": 6, "docs": 4.5, "ease_of_use": 4.2, "does_what_it_says": 5, "works_as_is": 5, "used_in_production": 5}, "fortiflexvm": {"quality_score": null, "score": 5.0, "count": 2, "docs": 5, "ease_of_use": 5, "does_what_it_says": 5, "works_as_is": 5, "used_in_production": 5}, "fortianalyzer": {"quality_score": null, "score": 5.0, "count": 1, "docs": 5, "ease_of_use": 5, "does_what_it_says": null, "works_as_is": null, "used_in_production": null}}, "netbox": {"netbox": {"quality_score": null, "score": 4.7, "count": 9, "docs": 4.3, "ease_of_use": 4.6, "does_what_it_says": 5, "works_as_is": 5, "used_in_production": 5}}, "awx": {"awx": {"quality_score": null, "score": 4.0, "count": 8, "docs": 3.9, "ease_of_use": 4.1, "does_what_it_says": 5, "works_as_is": 4.3, "used_in_production": 3.7}}, "freeipa": {"ansible_freeipa": {"quality_score": null, "score": 3.6, "count": 7, "docs": 4.1, "ease_of_use": 3.7, "does_what_it_says": 5, "works_as_is": 3.7, "used_in_production": 3}}, "dellemc": {"powermax": {"quality_score": null, "score": 3.8, "count": 6, "docs": 4.2, "ease_of_use": 4.3, "does_what_it_says": 3.7, "works_as_is": 4.3, "used_in_production": 3.7}, "openmanage": {"quality_score": null, "score": 5.0, "count": 6, "docs": 5, "ease_of_use": 5, "does_what_it_says": 5, "works_as_is": 5, "used_in_production": 5}, "powerflex": {"quality_score": null, "score": 5.0, "count": 3, "docs": 5, "ease_of_use": 5, "does_what_it_says": 5, "works_as_is": 5, "used_in_production": 5}, "os10": {"quality_score": null, "score": 2.8, "count": 2, "docs": 4, "ease_of_use": 3, "does_what_it_says": 3, "works_as_is": 3, "used_in_production": 3}, "powerstore": {"quality_score": null, "score": 5.0, "count": 1, "docs": 5, "ease_of_use": 5, "does_what_it_says": 5, "works_as_is": 5, "used_in_production": 5}, "unity": {"quality_score": null, "score": 5.0, "count": 1, "docs": 5, "ease_of_use": 5, "does_what_it_says": 5, "works_as_is": 5, "used_in_production": 5}, "powerscale": {"quality_score": null, "score": 5.0, "count": 1, "docs": 5, "ease_of_use": 5, "does_what_it_says": 5, "works_as_is": 5, "used_in_production": 5}, "vplex": {"quality_score": null, "score": 5.0, "count": 1, "docs": 5, "ease_of_use": 5, "does_what_it_says": 5, "works_as_is": 5, "used_in_production": 5}}, "azure": {"azcollection": {"quality_score": null, "score": 2.8, "count": 6, "docs": 2.8, "ease_of_use": 3.3, "does_what_it_says": 4.3, "works_as_is": 3.7, "used_in_production": 1.8}}, "netapp": {"ontap": {"quality_score": null, "score": 4.3, "count": 6, "docs": 4.7, "ease_of_use": 4.7, "does_what_it_says": 4.3, "works_as_is": 4.3, "used_in_production": 4.3}}, "ibm": {"power_aix": {"quality_score": null, "score": 3.9, "count": 6, "docs": 4.2, "ease_of_use": 4.8, "does_what_it_says": 4, "works_as_is": 3.4, "used_in_production": 4}, "ibm_zos_core": {"quality_score": null, "score": 5.0, "count": 4, "docs": 5, "ease_of_use": 5, "does_what_it_says": 5, "works_as_is": 5, "used_in_production": 5}, "ibm_zosmf": {"quality_score": null, "score": 5.0, "count": 3, "docs": 5, "ease_of_use": 5, "does_what_it_says": 5, "works_as_is": 5, "used_in_production": 5}, "power_aix_sap": {"quality_score": null, "score": 5.0, "count": 2, "docs": 5, "ease_of_use": 5, "does_what_it_says": 5, "works_as_is": 5, "used_in_production": 5}, "power_ibmi": {"quality_score": null, "score": 4.4, "count": 2, "docs": 3.5, "ease_of_use": 4, "does_what_it_says": 5, "works_as_is": 5, "used_in_production": 5}, "power_ibmi_sap": {"quality_score": null, "score": 5.0, "count": 2, "docs": 5, "ease_of_use": 5, "does_what_it_says": 5, "works_as_is": 5, "used_in_production": 5}, "isam": {"quality_score": null, "score": 1.1, "count": 2, "docs": 2.5, "ease_of_use": 1.5, "does_what_it_says": 5, "works_as_is": 1, "used_in_production": 1}, "ibm_zos_ims": {"quality_score": null, "score": 5.0, "count": 1, "docs": 5, "ease_of_use": 5, "does_what_it_says": 5, "works_as_is": 5, "used_in_production": 5}, "zos_cics_operator": {"quality_score": null, "score": 5.0, "count": 1, "docs": 5, "ease_of_use": 5, "does_what_it_says": 5, "works_as_is": 5, "used_in_production": 5}, "power_vios": {"quality_score": null, "score": 5.0, "count": 1, "docs": 5, "ease_of_use": 5, "does_what_it_says": 5, "works_as_is": 5, "used_in_production": 5}, "ibm_zos_sysauto": {"quality_score": null, "score": 5.0, "count": 1, "docs": 5, "ease_of_use": null, "does_what_it_says": 5, "works_as_is": null, "used_in_production": null}, "ibm_zos_zosmf": {"quality_score": null, "score": 5.0, "count": 1, "docs": 5, "ease_of_use": 5, "does_what_it_says": null, "works_as_is": null, "used_in_production": null}, "spectrum_virtualize": {"quality_score": null, "score": 5.0, "count": 1, "docs": 5, "ease_of_use": 5, "does_what_it_says": null, "works_as_is": null, "used_in_production": null}, "ibm_zos_cics": {"quality_score": null, "score": 5.0, "count": 1, "docs": 5, "ease_of_use": 5, "does_what_it_says": 5, "works_as_is": 5, "used_in_production": 5}, "power_hmc": {"quality_score": null, "score": 5.0, "count": 1, "docs": 5, "ease_of_use": 5, "does_what_it_says": 5, "works_as_is": 5, "used_in_production": 5}}, "openstack": {"cloud": {"quality_score": null, "score": 3.6, "count": 5, "docs": 2.8, "ease_of_use": 3.5, "does_what_it_says": 5, "works_as_is": 5, "used_in_production": 3.7}}, "yadvi12": {"kubernetesmultinodecluster": {"quality_score": null, "score": 4.8, "count": 5, "docs": 5, "ease_of_use": 4.8, "does_what_it_says": 5, "works_as_is": 5, "used_in_production": 4.2}}, "davidban77": {"gns3": {"quality_score": null, "score": 5.0, "count": 5, "docs": 5, "ease_of_use": 5, "does_what_it_says": 5, "works_as_is": 5, "used_in_production": 5}}, "cyberark": {"pas": {"quality_score": null, "score": 1.0, "count": 5, "docs": 2, "ease_of_use": 2, "does_what_it_says": 3, "works_as_is": 1, "used_in_production": 1}}, "infoblox": {"nios_modules": {"quality_score": null, "score": 2.7, "count": 5, "docs": 3.4, "ease_of_use": 3.2, "does_what_it_says": 4, "works_as_is": 2.6, "used_in_production": 2.6}}, "purestorage": {"flasharray": {"quality_score": null, "score": 4.0, "count": 4, "docs": 4.5, "ease_of_use": 4.2, "does_what_it_says": 5, "works_as_is": 3.7, "used_in_production": 3.7}, "flashblade": {"quality_score": null, "score": 5.0, "count": 1, "docs": 5, "ease_of_use": 5, "does_what_it_says": 5, "works_as_is": 5, "used_in_production": 5}, "fusion": {"quality_score": null, "score": 5.0, "count": 1, "docs": 5, "ease_of_use": 5, "does_what_it_says": 5, "works_as_is": 5, "used_in_production": 5}}, "dealtalfa": {"kubernetes": {"quality_score": null, "score": 5.0, "count": 4, "docs": 5, "ease_of_use": 5, "does_what_it_says": 5, "works_as_is": 5, "used_in_production": 5}}, "nokia": {"sros": {"quality_score": null, "score": 4.9, "count": 4, "docs": 4.7, "ease_of_use": 5, "does_what_it_says": 5, "works_as_is": 5, "used_in_production": 5}, "openconfig": {"quality_score": null, "score": 5.0, "count": 2, "docs": 5, "ease_of_use": 5, "does_what_it_says": 5, "works_as_is": 5, "used_in_production": 5}, "grpc": {"quality_score": null, "score": 5.0, "count": 1, "docs": 5, "ease_of_use": 5, "does_what_it_says": 5, "works_as_is": 5, "used_in_production": 5}}, "containers": {"podman": {"quality_score": null, "score": 4.1, "count": 4, "docs": 4, "ease_of_use": 4.5, "does_what_it_says": 4, "works_as_is": 5, "used_in_production": 4}}, "nginxinc": {"nginx_core": {"quality_score": null, "score": 3.0, "count": 4, "docs": 2, "ease_of_use": 3.3, "does_what_it_says": 5, "works_as_is": 3.7, "used_in_production": 3.7}, "nginx_controller": {"quality_score": null, "score": 5.0, "count": 1, "docs": 5, "ease_of_use": 5, "does_what_it_says": 5, "works_as_is": 5, "used_in_production": 5}}, "edb_devops": {"edb_postgres": {"quality_score": null, "score": 4.9, "count": 4, "docs": 5, "ease_of_use": 4.8, "does_what_it_says": 5, "works_as_is": 5, "used_in_production": 5}}, "robertdebock": {"roles": {"quality_score": null, "score": 4.6, "count": 4, "docs": 4, "ease_of_use": 5, "does_what_it_says": 5, "works_as_is": 5, "used_in_production": 5}, "development_environment": {"quality_score": null, "score": 5.0, "count": 1, "docs": null, "ease_of_use": 5, "does_what_it_says": null, "works_as_is": null, "used_in_production": null}}, "hetzner": {"hcloud": {"quality_score": null, "score": 5.0, "count": 4, "docs": 5, "ease_of_use": 5, "does_what_it_says": 5, "works_as_is": 5, "used_in_production": 5}}, "redhat_cop": {"tower_configuration": {"quality_score": null, "score": 4.6, "count": 4, "docs": 4.8, "ease_of_use": 4.8, "does_what_it_says": 5, "works_as_is": 5, "used_in_production": 4}, "ah_configuration": {"quality_score": null, "score": 5.0, "count": 3, "docs": 5, "ease_of_use": 5, "does_what_it_says": 5, "works_as_is": 5, "used_in_production": 5}, "controller_configuration": {"quality_score": null, "score": 5.0, "count": 1, "docs": 5, "ease_of_use": 5, "does_what_it_says": 5, "works_as_is": 5, "used_in_production": 5}, "aap_utilities": {"quality_score": null, "score": 5.0, "count": 1, "docs": 5, "ease_of_use": 5, "does_what_it_says": 5, "works_as_is": 5, "used_in_production": 5}}, "f5networks": {"f5_modules": {"quality_score": null, "score": 4.7, "count": 4, "docs": 5, "ease_of_use": 5, "does_what_it_says": 4, "works_as_is": 5, "used_in_production": 5}}, "manala": {"roles": {"quality_score": null, "score": 3.8, "count": 4, "docs": 4, "ease_of_use": 4.2, "does_what_it_says": 4, "works_as_is": 4, "used_in_production": 4}}, "ansible": {"posix": {"quality_score": null, "score": 5.0, "count": 4, "docs": 5, "ease_of_use": 5, "does_what_it_says": 5, "works_as_is": 5, "used_in_production": 5}, "netcommon": {"quality_score": null, "score": 4.2, "count": 2, "docs": 3, "ease_of_use": 5, "does_what_it_says": 5, "works_as_is": 5, "used_in_production": 5}, "product_demos": {"quality_score": null, "score": 5.0, "count": 1, "docs": 5, "ease_of_use": 5, "does_what_it_says": 5, "works_as_is": 5, "used_in_production": 5}, "utils": {"quality_score": null, "score": 5.0, "count": 1, "docs": 5, "ease_of_use": 5, "does_what_it_says": 5, "works_as_is": 5, "used_in_production": 5}, "windows": {"quality_score": null, "score": 4.8, "count": 1, "docs": 4, "ease_of_use": 5, "does_what_it_says": 5, "works_as_is": 5, "used_in_production": 5}}, "google": {"cloud": {"quality_score": null, "score": 2.2, "count": 3, "docs": 3.7, "ease_of_use": 3, "does_what_it_says": 3.7, "works_as_is": 2.3, "used_in_production": 1}}, "cankush625": {"kubernetescluster": {"quality_score": null, "score": 4.6, "count": 3, "docs": 4.7, "ease_of_use": 5, "does_what_it_says": 5, "works_as_is": 3.7, "used_in_production": 5}, "bigdata_hadoop": {"quality_score": null, "score": 5.0, "count": 1, "docs": 5, "ease_of_use": 5, "does_what_it_says": 5, "works_as_is": 5, "used_in_production": 5}}, "check_point": {"gaia": {"quality_score": null, "score": 2.7, "count": 3, "docs": 3.7, "ease_of_use": 3.7, "does_what_it_says": 2.3, "works_as_is": 3.7, "used_in_production": 2.3}, "mgmt": {"quality_score": null, "score": 4.5, "count": 2, "docs": 4, "ease_of_use": 4, "does_what_it_says": 5, "works_as_is": 5, "used_in_production": 5}}, "scicore": {"guacamole": {"quality_score": null, "score": 3.7, "count": 3, "docs": 4.3, "ease_of_use": 4.7, "does_what_it_says": 5, "works_as_is": 3.7, "used_in_production": 2.3}}, "radware": {"radware_modules": {"quality_score": null, "score": 5.0, "count": 3, "docs": 5, "ease_of_use": 5, "does_what_it_says": 5, "works_as_is": 5, "used_in_production": 5}}, "arubanetworks": {"aoscx": {"quality_score": null, "score": 5.0, "count": 3, "docs": 5, "ease_of_use": 5, "does_what_it_says": 5, "works_as_is": null, "used_in_production": null}, "aos_switch": {"quality_score": null, "score": 1.8, "count": 3, "docs": 2.7, "ease_of_use": 2.3, "does_what_it_says": 2.3, "works_as_is": 2.3, "used_in_production": 2.3}, "aruba_central": {"quality_score": null, "score": null, "count": 1, "docs": 1, "ease_of_use": null, "does_what_it_says": null, "works_as_is": null, "used_in_production": null}}, "geerlingguy": {"php_roles": {"quality_score": null, "score": 4.1, "count": 3, "docs": 5, "ease_of_use": 5, "does_what_it_says": 5, "works_as_is": 3, "used_in_production": 3.7}, "k8s": {"quality_score": null, "score": 5.0, "count": 1, "docs": null, "ease_of_use": null, "does_what_it_says": null, "works_as_is": null, "used_in_production": 5}, "mac": {"quality_score": null, "score": 5.0, "count": 1, "docs": 5, "ease_of_use": 5, "does_what_it_says": 5, "works_as_is": 5, "used_in_production": null}}, "fedora": {"linux_system_roles": {"quality_score": null, "score": 3.5, "count": 3, "docs": 2.7, "ease_of_use": 2.7, "does_what_it_says": 5, "works_as_is": 5, "used_in_production": 5}}, "paloaltonetworks": {"panos": {"quality_score": null, "score": 3.5, "count": 3, "docs": 3.3, "ease_of_use": 3.7, "does_what_it_says": 5, "works_as_is": 3, "used_in_production": 3.7}}, "code_egg": {"openlitespeed_wordpress": {"quality_score": null, "score": 3.2, "count": 3, "docs": 4.7, "ease_of_use": 3.7, "does_what_it_says": 3, "works_as_is": 3, "used_in_production": 3}}, "chocolatey": {"chocolatey": {"quality_score": null, "score": 4.4, "count": 3, "docs": 5, "ease_of_use": 5, "does_what_it_says": 3, "works_as_is": 5, "used_in_production": 5}}, "alikins": {"collection_inspect": {"quality_score": null, "score": 3.8, "count": 3, "docs": 2.7, "ease_of_use": 3.7, "does_what_it_says": 5, "works_as_is": 5, "used_in_production": 3.7}}, "idmsubs": {"manageengine": {"quality_score": null, "score": 5.0, "count": 2, "docs": 5, "ease_of_use": 5, "does_what_it_says": 5, "works_as_is": 5, "used_in_production": 5}, "rapid7_insightvm": {"quality_score": null, "score": 5.0, "count": 2, "docs": 5, "ease_of_use": 5, "does_what_it_says": 5, "works_as_is": 5, "used_in_production": 5}}, "maxhoesel": {"caddy": {"quality_score": null, "score": 1.8, "count": 2, "docs": 3.5, "ease_of_use": 3.5, "does_what_it_says": 1, "works_as_is": 1, "used_in_production": 1}, "smallstep": {"quality_score": null, "score": 5.0, "count": 1, "docs": 5, "ease_of_use": 5, "does_what_it_says": 5, "works_as_is": 5, "used_in_production": 5}}, "ibmcloud": {"ibmcollection": {"quality_score": null, "score": 1.9, "count": 2, "docs": 2, "ease_of_use": 1.5, "does_what_it_says": 5, "works_as_is": 3, "used_in_production": 1}}, "kubernetes": {"core": {"quality_score": null, "score": 4.4, "count": 2, "docs": 4, "ease_of_use": 4.5, "does_what_it_says": 5, "works_as_is": null, "used_in_production": 5}}, "crivetimihai": {"virtualization": {"quality_score": null, "score": 3.8, "count": 2, "docs": 1, "ease_of_use": 4, "does_what_it_says": 5, "works_as_is": 5, "used_in_production": 5}, "server": {"quality_score": null, "score": 4.0, "count": 2, "docs": 4, "ease_of_use": 4, "does_what_it_says": 3, "works_as_is": 5, "used_in_production": 5}}, "sindhuparvathi_gopi": {"ansible_collection_template": {"quality_score": null, "score": 0.6, "count": 2, "docs": 2.5, "ease_of_use": 1, "does_what_it_says": 1, "works_as_is": 1, "used_in_production": 1}}, "ericsysmin": {"system": {"quality_score": null, "score": 3.8, "count": 2, "docs": 4.5, "ease_of_use": 4.5, "does_what_it_says": 5, "works_as_is": 3, "used_in_production": 3}}, "clay584": {"genie": {"quality_score": null, "score": 4.9, "count": 2, "docs": 5, "ease_of_use": 4.5, "does_what_it_says": 5, "works_as_is": 5, "used_in_production": 5}}, "citrix": {"adc": {"quality_score": null, "score": 4.0, "count": 2, "docs": 5, "ease_of_use": 5, "does_what_it_says": 5, "works_as_is": 5, "used_in_production": 1}}, "chrismeyersfsu": {"tower_modules": {"quality_score": null, "score": 2.3, "count": 2, "docs": 3, "ease_of_use": 2.5, "does_what_it_says": 5, "works_as_is": null, "used_in_production": 1}}, "servicenow": {"servicenow": {"quality_score": null, "score": 2.1, "count": 2, "docs": 2, "ease_of_use": 2.5, "does_what_it_says": 3, "works_as_is": 3, "used_in_production": 3}}, "sva": {"sentinelone": {"quality_score": null, "score": 5.0, "count": 2, "docs": 5, "ease_of_use": 5, "does_what_it_says": 5, "works_as_is": 5, "used_in_production": 5}}, "debops": {"debops": {"quality_score": null, "score": 4.9, "count": 2, "docs": 4.5, "ease_of_use": 5, "does_what_it_says": 5, "works_as_is": 5, "used_in_production": 5}}, "appdynamics": {"agents": {"quality_score": null, "score": 5.0, "count": 2, "docs": 5, "ease_of_use": 5, "does_what_it_says": 5, "works_as_is": 5, "used_in_production": 5}}, "jfrog": {"installers": {"quality_score": null, "score": 0.5, "count": 2, "docs": 2.5, "ease_of_use": 1.5, "does_what_it_says": 1, "works_as_is": 1, "used_in_production": 1}, "platform": {"quality_score": null, "score": null, "count": 1, "docs": 1, "ease_of_use": 1, "does_what_it_says": 1, "works_as_is": 1, "used_in_production": 1}}, "arista": {"cvp": {"quality_score": null, "score": 4.4, "count": 2, "docs": 5, "ease_of_use": 3.5, "does_what_it_says": 5, "works_as_is": 5, "used_in_production": 5}, "avd": {"quality_score": null, "score": 5.0, "count": 2, "docs": 5, "ease_of_use": 5, "does_what_it_says": 5, "works_as_is": 5, "used_in_production": 5}, "eos": {"quality_score": null, "score": 5.0, "count": 1, "docs": 5, "ease_of_use": 5, "does_what_it_says": 5, "works_as_is": 5, "used_in_production": null}}, "tribe29": {"checkmk": {"quality_score": null, "score": 4.2, "count": 2, "docs": 4.5, "ease_of_use": 4.5, "does_what_it_says": 5, "works_as_is": 5, "used_in_production": 1}}, "scale_computing": {"hypercore": {"quality_score": null, "score": 5.0, "count": 2, "docs": 5, "ease_of_use": 5, "does_what_it_says": 5, "works_as_is": 5, "used_in_production": 5}}, "microsoft": {"sql": {"quality_score": null, "score": 5.0, "count": 2, "docs": 5, "ease_of_use": 5, "does_what_it_says": 5, "works_as_is": 5, "used_in_production": 5}, "ad": {"quality_score": null, "score": 5.0, "count": 1, "docs": 5, "ease_of_use": 5, "does_what_it_says": 5, "works_as_is": 5, "used_in_production": 5}}, "alexanderbazhenoff": {"linux": {"quality_score": null, "score": 4.0, "count": 2, "docs": 4, "ease_of_use": 4, "does_what_it_says": 3, "works_as_is": 5, "used_in_production": 5}}, "brocade": {"fos": {"quality_score": null, "score": 3.4, "count": 2, "docs": 3.5, "ease_of_use": 4, "does_what_it_says": 5, "works_as_is": 5, "used_in_production": 1}}, "hazel_shen": {"line_notify": {"quality_score": null, "score": 1.9, "count": 2, "docs": 1, "ease_of_use": 3, "does_what_it_says": 3, "works_as_is": 3, "used_in_production": 1}}, "openafs_contrib": {"openafs": {"quality_score": null, "score": 5.0, "count": 2, "docs": 5, "ease_of_use": 5, "does_what_it_says": 5, "works_as_is": 5, "used_in_production": 5}}, "pandemonium1986": {"k8s_toolbox": {"quality_score": null, "score": 5.0, "count": 2, "docs": 5, "ease_of_use": 5, "does_what_it_says": 5, "works_as_is": 5, "used_in_production": 5}, "openstack": {"quality_score": null, "score": 1.7, "count": 1, "docs": null, "ease_of_use": null, "does_what_it_says": 5, "works_as_is": 1, "used_in_production": 1}}, "serverscom": {"mitogen": {"quality_score": null, "score": 5.0, "count": 2, "docs": 5, "ease_of_use": 5, "does_what_it_says": 5, "works_as_is": 5, "used_in_production": 5}}, "nttmcp": {"mcp": {"quality_score": null, "score": 5.0, "count": 2, "docs": 5, "ease_of_use": 5, "does_what_it_says": 5, "works_as_is": 5, "used_in_production": 5}}, "devsec": {"hardening": {"quality_score": null, "score": 4.5, "count": 2, "docs": 3, "ease_of_use": 5, "does_what_it_says": 5, "works_as_is": 5, "used_in_production": 5}}, "solace": {"pubsub_plus": {"quality_score": null, "score": 5.0, "count": 1, "docs": 5, "ease_of_use": 5, "does_what_it_says": 5, "works_as_is": 5, "used_in_production": 5}}, "newswangerd": {"collection_demo": {"quality_score": null, "score": null, "count": 1, "docs": 1, "ease_of_use": null, "does_what_it_says": null, "works_as_is": null, "used_in_production": null}}, "steampunk": {"aws": {"quality_score": null, "score": 5.0, "count": 1, "docs": 5, "ease_of_use": 5, "does_what_it_says": 5, "works_as_is": 5, "used_in_production": 5}}, "ari_stark": {"ansible_oracle_modules": {"quality_score": null, "score": 5.0, "count": 1, "docs": 5, "ease_of_use": 5, "does_what_it_says": 5, "works_as_is": 5, "used_in_production": 5}}, "ionoscloudsdk": {"ionoscloud": {"quality_score": null, "score": 5.0, "count": 1, "docs": null, "ease_of_use": null, "does_what_it_says": null, "works_as_is": null, "used_in_production": 5}}, "markuman": {"hetzner_dns": {"quality_score": null, "score": 5.0, "count": 1, "docs": 5, "ease_of_use": 5, "does_what_it_says": 5, "works_as_is": 5, "used_in_production": 5}}, "cybus": {"connectware": {"quality_score": null, "score": 4.2, "count": 1, "docs": 2, "ease_of_use": 5, "does_what_it_says": 5, "works_as_is": 5, "used_in_production": 5}}, "elfelip": {"keycloak": {"quality_score": null, "score": 2.2, "count": 1, "docs": 3, "ease_of_use": 4, "does_what_it_says": 5, "works_as_is": 1, "used_in_production": 1}}, "amazon": {"aws": {"quality_score": null, "score": 4.5, "count": 1, "docs": 5, "ease_of_use": 3, "does_what_it_says": 5, "works_as_is": 5, "used_in_production": 5}, "cloud": {"quality_score": null, "score": 5.0, "count": 1, "docs": 5, "ease_of_use": null, "does_what_it_says": 5, "works_as_is": 5, "used_in_production": null}}, "rbrightling": {"system": {"quality_score": null, "score": 5.0, "count": 1, "docs": 5, "ease_of_use": 5, "does_what_it_says": 5, "works_as_is": 5, "used_in_production": 5}}, "pfsensible": {"core": {"quality_score": null, "score": 5.0, "count": 1, "docs": 5, "ease_of_use": 5, "does_what_it_says": 5, "works_as_is": 5, "used_in_production": 5}}, "ovirt": {"ovirt": {"quality_score": null, "score": 5.0, "count": 1, "docs": 5, "ease_of_use": 5, "does_what_it_says": 5, "works_as_is": 5, "used_in_production": 5}}, "sivel": {"toiletwater": {"quality_score": null, "score": 5.0, "count": 1, "docs": 5, "ease_of_use": 5, "does_what_it_says": 5, "works_as_is": 5, "used_in_production": 5}}, "kewlfft": {"aur": {"quality_score": null, "score": 5.0, "count": 1, "docs": 5, "ease_of_use": 5, "does_what_it_says": 5, "works_as_is": 5, "used_in_production": 5}}, "oasis_roles": {"system": {"quality_score": null, "score": null, "count": 1, "docs": 1, "ease_of_use": null, "does_what_it_says": null, "works_as_is": null, "used_in_production": null}}, "univention": {"ucs_modules": {"quality_score": null, "score": 4.1, "count": 1, "docs": 3, "ease_of_use": 4, "does_what_it_says": 5, "works_as_is": 5, "used_in_production": null}}, "prometheus": {"prometheus": {"quality_score": null, "score": 5.0, "count": 1, "docs": 5, "ease_of_use": 5, "does_what_it_says": 5, "works_as_is": 5, "used_in_production": 5}}, "crowdstrike": {"falcon": {"quality_score": null, "score": 5.0, "count": 1, "docs": 5, "ease_of_use": 5, "does_what_it_says": 5, "works_as_is": 5, "used_in_production": 5}}, "lvrfrc87": {"git_acp": {"quality_score": null, "score": 4.8, "count": 1, "docs": 4, "ease_of_use": 5, "does_what_it_says": 5, "works_as_is": 5, "used_in_production": 5}}, "redhatinsights": {"insights": {"quality_score": null, "score": 4.5, "count": 1, "docs": 3, "ease_of_use": 5, "does_what_it_says": 5, "works_as_is": 5, "used_in_production": 5}}, "theforeman": {"foreman": {"quality_score": null, "score": 5.0, "count": 1, "docs": 5, "ease_of_use": 5, "does_what_it_says": 5, "works_as_is": 5, "used_in_production": 5}}, "l3d": {"git": {"quality_score": null, "score": 5.0, "count": 1, "docs": 5, "ease_of_use": 5, "does_what_it_says": 5, "works_as_is": 5, "used_in_production": 5}}, "bvollmerhaus": {"matrix_dendrite": {"quality_score": null, "score": 5.0, "count": 1, "docs": 5, "ease_of_use": 5, "does_what_it_says": 5, "works_as_is": 5, "used_in_production": 5}}, "utoddl": {"logical": {"quality_score": null, "score": 5.0, "count": 1, "docs": 5, "ease_of_use": 5, "does_what_it_says": 5, "works_as_is": 5, "used_in_production": 5}}, "netbox_community": {"ansible_modules": {"quality_score": null, "score": 4.8, "count": 1, "docs": 4, "ease_of_use": 5, "does_what_it_says": 5, "works_as_is": 5, "used_in_production": 5}}, "rshad": {"collection_demo": {"quality_score": null, "score": null, "count": 1, "docs": 1, "ease_of_use": 1, "does_what_it_says": 1, "works_as_is": 1, "used_in_production": 1}}, "nn708": {"openwrt": {"quality_score": null, "score": 5.0, "count": 1, "docs": 5, "ease_of_use": 5, "does_what_it_says": 5, "works_as_is": 5, "used_in_production": 5}}, "juniper": {"space": {"quality_score": null, "score": 5.0, "count": 1, "docs": 5, "ease_of_use": 5, "does_what_it_says": 5, "works_as_is": 5, "used_in_production": 5}}, "anastasiaerhan": {"infrastructure": {"quality_score": null, "score": null, "count": 1, "docs": 1, "ease_of_use": null, "does_what_it_says": null, "works_as_is": null, "used_in_production": null}}, "sundari_28": {"firstcoll": {"quality_score": null, "score": 5.0, "count": 1, "docs": 5, "ease_of_use": 5, "does_what_it_says": 5, "works_as_is": 5, "used_in_production": 5}, "elastic_runtime": {"quality_score": null, "score": 5.0, "count": 1, "docs": 5, "ease_of_use": 5, "does_what_it_says": 5, "works_as_is": 5, "used_in_production": 5}}, "enmanuelmoreira": {"calibre": {"quality_score": null, "score": 0.8, "count": 1, "docs": 3, "ease_of_use": 1, "does_what_it_says": null, "works_as_is": null, "used_in_production": 1}}, "emxkd": {"k8s_cluster_collection": {"quality_score": null, "score": 4.0, "count": 1, "docs": 5, "ease_of_use": 5, "does_what_it_says": 5, "works_as_is": 1, "used_in_production": 5}}, "mafalb": {"restic": {"quality_score": null, "score": 1.2, "count": 1, "docs": 2, "ease_of_use": null, "does_what_it_says": null, "works_as_is": null, "used_in_production": null}}, "rahulgitx": {"ans_kube": {"quality_score": null, "score": 5.0, "count": 1, "docs": 5, "ease_of_use": 5, "does_what_it_says": 5, "works_as_is": 5, "used_in_production": 5}}, "lyr": {"opendistrocollection": {"quality_score": null, "score": 4.0, "count": 1, "docs": 5, "ease_of_use": 5, "does_what_it_says": 5, "works_as_is": 5, "used_in_production": 1}}, "zzbytes": {"redteam": {"quality_score": null, "score": null, "count": 1, "docs": 1, "ease_of_use": 1, "does_what_it_says": 1, "works_as_is": 1, "used_in_production": 1}}, "pishro_cloud": {"zabbix": {"quality_score": null, "score": null, "count": 1, "docs": 1, "ease_of_use": 1, "does_what_it_says": 1, "works_as_is": 1, "used_in_production": 1}}, "devoperate": {"base": {"quality_score": null, "score": 4.4, "count": 1, "docs": 4, "ease_of_use": 5, "does_what_it_says": null, "works_as_is": null, "used_in_production": null}}, "nikhil9546": {"multinodecluster": {"quality_score": null, "score": 5.0, "count": 1, "docs": 5, "ease_of_use": 5, "does_what_it_says": 5, "works_as_is": 5, "used_in_production": 5}}, "nikhilpatne": {"manageengine": {"quality_score": null, "score": 5.0, "count": 1, "docs": 5, "ease_of_use": 5, "does_what_it_says": 5, "works_as_is": 5, "used_in_production": 5}}, "redhatchris": {"foobar": {"quality_score": null, "score": 5.0, "count": 1, "docs": 5, "ease_of_use": 5, "does_what_it_says": 5, "works_as_is": 5, "used_in_production": 5}}, "digitalocean": {"cloud": {"quality_score": null, "score": 5.0, "count": 1, "docs": 5, "ease_of_use": 5, "does_what_it_says": 5, "works_as_is": 5, "used_in_production": 5}}, "marshalw": {"traefik_deploy": {"quality_score": null, "score": null, "count": 1, "docs": 1, "ease_of_use": null, "does_what_it_says": null, "works_as_is": null, "used_in_production": null}}, "julien_lecomte": {"roster": {"quality_score": null, "score": 4.8, "count": 1, "docs": 4, "ease_of_use": 5, "does_what_it_says": 5, "works_as_is": 5, "used_in_production": 5}, "proxmox": {"quality_score": null, "score": 5.0, "count": 1, "docs": 5, "ease_of_use": 5, "does_what_it_says": 5, "works_as_is": 5, "used_in_production": 5}}, "cohesity": {"dataprotect": {"quality_score": null, "score": 5.0, "count": 1, "docs": null, "ease_of_use": null, "does_what_it_says": 5, "works_as_is": null, "used_in_production": 5}}, "o1labs": {"crypto": {"quality_score": null, "score": 5.0, "count": 1, "docs": 5, "ease_of_use": 5, "does_what_it_says": 5, "works_as_is": 5, "used_in_production": 5}}, "apidb": {"apidb_collection": {"quality_score": null, "score": 5.0, "count": 1, "docs": 5, "ease_of_use": 5, "does_what_it_says": 5, "works_as_is": 5, "used_in_production": 5}}, "subhashis2": {"k8smultinodeclusteronaws": {"quality_score": null, "score": 5.0, "count": 1, "docs": 5, "ease_of_use": 5, "does_what_it_says": 5, "works_as_is": 5, "used_in_production": 5}}, "ivansible": {"ndms": {"quality_score": null, "score": 0.5, "count": 1, "docs": 2, "ease_of_use": 2, "does_what_it_says": 1, "works_as_is": 1, "used_in_production": 1}}, "goldeagle": {"develop": {"quality_score": null, "score": null, "count": 1, "docs": null, "ease_of_use": null, "does_what_it_says": null, "works_as_is": null, "used_in_production": 1}}, "dsglaser": {"cis_security": {"quality_score": null, "score": 5.0, "count": 1, "docs": 5, "ease_of_use": null, "does_what_it_says": null, "works_as_is": null, "used_in_production": null}}, "molgenis": {"molgenis10": {"quality_score": null, "score": 1.5, "count": 1, "docs": 1, "ease_of_use": 3, "does_what_it_says": 5, "works_as_is": 1, "used_in_production": 1}, "molgenis8": {"quality_score": null, "score": 2.8, "count": 1, "docs": 2, "ease_of_use": 3, "does_what_it_says": 5, "works_as_is": 1, "used_in_production": 5}}, "ciena": {"saos6": {"quality_score": null, "score": 4.2, "count": 1, "docs": 3, "ease_of_use": 4, "does_what_it_says": 5, "works_as_is": 5, "used_in_production": 5}}, "opennebula": {"cloud": {"quality_score": null, "score": null, "count": 1, "docs": 1, "ease_of_use": 1, "does_what_it_says": 1, "works_as_is": 1, "used_in_production": 1}}, "quantasw": {"qnos": {"quality_score": null, "score": 5.0, "count": 1, "docs": 5, "ease_of_use": 5, "does_what_it_says": 5, "works_as_is": 5, "used_in_production": 5}}, "kbreit": {"meraki": {"quality_score": null, "score": 5.0, "count": 1, "docs": 5, "ease_of_use": 5, "does_what_it_says": 5, "works_as_is": 5, "used_in_production": 5}}, "daniel_chung_broadcom": {"fos": {"quality_score": null, "score": 2.5, "count": 1, "docs": 3, "ease_of_use": 3, "does_what_it_says": null, "works_as_is": null, "used_in_production": null}}, "debendraoli": {"node_exporter": {"quality_score": null, "score": null, "count": 1, "docs": 1, "ease_of_use": 1, "does_what_it_says": 1, "works_as_is": 1, "used_in_production": 1}}, "ansilab": {"demo_one": {"quality_score": null, "score": 5.0, "count": 1, "docs": null, "ease_of_use": null, "does_what_it_says": 5, "works_as_is": null, "used_in_production": null}}, "carlos_zrm": {"teams_msg": {"quality_score": null, "score": null, "count": 1, "docs": 1, "ease_of_use": 1, "does_what_it_says": null, "works_as_is": null, "used_in_production": null}}, "goldyfruit": {"ibmcloud_automation": {"quality_score": null, "score": 5.0, "count": 1, "docs": 5, "ease_of_use": 5, "does_what_it_says": 5, "works_as_is": 5, "used_in_production": 5}}, "usegalaxy_eu": {"handy": {"quality_score": null, "score": 5.0, "count": 1, "docs": 5, "ease_of_use": 5, "does_what_it_says": 5, "works_as_is": 5, "used_in_production": 5}}, "sedi": {"openaudit": {"quality_score": null, "score": 4.8, "count": 1, "docs": 5, "ease_of_use": 4, "does_what_it_says": 5, "works_as_is": 5, "used_in_production": 5}}, "klusters": {"elasticsearch": {"quality_score": null, "score": null, "count": 1, "docs": 1, "ease_of_use": null, "does_what_it_says": null, "works_as_is": null, "used_in_production": null}}, "joellefkowitz": {"swarmroles": {"quality_score": null, "score": 5.0, "count": 1, "docs": 5, "ease_of_use": 5, "does_what_it_says": 5, "works_as_is": 5, "used_in_production": 5}}, "cremsburg": {"mist": {"quality_score": null, "score": null, "count": 1, "docs": 1, "ease_of_use": null, "does_what_it_says": 1, "works_as_is": 1, "used_in_production": 1}}, "rudder": {"rudder": {"quality_score": null, "score": 5.0, "count": 1, "docs": 5, "ease_of_use": 5, "does_what_it_says": 5, "works_as_is": 5, "used_in_production": 5}}, "amotolani": {"cisco_fmc": {"quality_score": null, "score": 5.0, "count": 1, "docs": 5, "ease_of_use": 5, "does_what_it_says": 5, "works_as_is": 5, "used_in_production": 5}}, "shuntps": {"docker_container": {"quality_score": null, "score": 4.7, "count": 1, "docs": null, "ease_of_use": 4, "does_what_it_says": 5, "works_as_is": 5, "used_in_production": 5}}, "tvartom": {"serveradmin": {"quality_score": null, "score": null, "count": 1, "docs": 1, "ease_of_use": null, "does_what_it_says": null, "works_as_is": null, "used_in_production": null}}, "jagadeeshnv": {"test2": {"quality_score": null, "score": null, "count": 1, "docs": 1, "ease_of_use": 1, "does_what_it_says": 1, "works_as_is": 1, "used_in_production": 1}}, "mistermiles": {"gpg_key_import": {"quality_score": null, "score": null, "count": 1, "docs": 1, "ease_of_use": 1, "does_what_it_says": 1, "works_as_is": 1, "used_in_production": 1}}, "diademiemi": {"jetbrains": {"quality_score": null, "score": null, "count": 1, "docs": 1, "ease_of_use": null, "does_what_it_says": 1, "works_as_is": null, "used_in_production": 1}}, "merative": {"spm_middleware": {"quality_score": null, "score": 5.0, "count": 1, "docs": 5, "ease_of_use": 5, "does_what_it_says": 5, "works_as_is": 5, "used_in_production": 5}}, "mhansen": {"ansible_trace": {"quality_score": null, "score": 5.0, "count": 1, "docs": 5, "ease_of_use": 5, "does_what_it_says": 5, "works_as_is": 5, "used_in_production": 5}}, "inspur": {"sm": {"quality_score": null, "score": 1.2, "count": 1, "docs": 2, "ease_of_use": 1, "does_what_it_says": 1, "works_as_is": 5, "used_in_production": 1}}, "finallycoffee": {"nextcloud": {"quality_score": null, "score": 5.0, "count": 1, "docs": 5, "ease_of_use": 5, "does_what_it_says": 5, "works_as_is": 5, "used_in_production": 5}}, "kubeinit": {"kubeinit": {"quality_score": null, "score": 5.0, "count": 1, "docs": 5, "ease_of_use": 5, "does_what_it_says": null, "works_as_is": null, "used_in_production": null}}, "jonellis": {"sudoers": {"quality_score": null, "score": 2.5, "count": 1, "docs": 4, "ease_of_use": 4, "does_what_it_says": 5, "works_as_is": 1, "used_in_production": 1}}, "huaweidatacom": {"ne": {"quality_score": null, "score": 5.0, "count": 1, "docs": 5, "ease_of_use": 5, "does_what_it_says": null, "works_as_is": null, "used_in_production": null}}, "stolostron": {"core": {"quality_score": null, "score": 5.0, "count": 1, "docs": 5, "ease_of_use": 5, "does_what_it_says": null, "works_as_is": null, "used_in_production": null}}, "serdigital64": {"system": {"quality_score": null, "score": 4.0, "count": 1, "docs": 3, "ease_of_use": 3, "does_what_it_says": 5, "works_as_is": 5, "used_in_production": 5}, "monitor": {"quality_score": null, "score": 5.0, "count": 1, "docs": 5, "ease_of_use": 5, "does_what_it_says": 5, "works_as_is": 5, "used_in_production": 5}}, "ngine_io": {"vultr": {"quality_score": null, "score": 4.2, "count": 1, "docs": 3, "ease_of_use": 4, "does_what_it_says": 5, "works_as_is": 5, "used_in_production": 5}}, "waghmaredb": {"dellemc_universal_csi_installer": {"quality_score": null, "score": 5.0, "count": 1, "docs": 5, "ease_of_use": 5, "does_what_it_says": 5, "works_as_is": 5, "used_in_production": 5}}, "marmorag": {"ansodium": {"quality_score": null, "score": 4.0, "count": 1, "docs": 3, "ease_of_use": 3, "does_what_it_says": 5, "works_as_is": 5, "used_in_production": 5}}, "alvistack": {"kubernetes": {"quality_score": null, "score": 5.0, "count": 1, "docs": 5, "ease_of_use": 5, "does_what_it_says": 5, "works_as_is": 5, "used_in_production": 5}}, "hitachi": {"raidcom": {"quality_score": null, "score": 2.5, "count": 1, "docs": 1, "ease_of_use": 3, "does_what_it_says": 5, "works_as_is": 5, "used_in_production": 1}}, "netapp_eseries": {"santricity": {"quality_score": null, "score": 5.0, "count": 1, "docs": 5, "ease_of_use": 5, "does_what_it_says": 5, "works_as_is": 5, "used_in_production": 5}}, "pureport": {"pureport": {"quality_score": null, "score": null, "count": 1, "docs": 1, "ease_of_use": 1, "does_what_it_says": null, "works_as_is": null, "used_in_production": null}}, "hpe": {"oneview": {"quality_score": null, "score": 4.5, "count": 1, "docs": 4, "ease_of_use": 4, "does_what_it_says": 5, "works_as_is": 5, "used_in_production": 5}}, "senhasegura": {"pam": {"quality_score": null, "score": 5.0, "count": 1, "docs": 5, "ease_of_use": 5, "does_what_it_says": 5, "works_as_is": 5, "used_in_production": 5}}}